dslinter/__init__.py
dslinter/checkers/__init__.py
dslinter/checkers/chain_indexing_pandas.py
dslinter/checkers/column_selection_pandas.py
dslinter/checkers/dataframe_conversion_pandas.py
dslinter/checkers/datatype_pandas.py
dslinter/checkers/dependent_threshold_pytorch.py
dslinter/checkers/dependent_threshold_scikitlearn.py
dslinter/checkers/dependent_threshold_tensorflow.py
dslinter/checkers/deprecated/__init__.py
dslinter/checkers/deprecated/inplace_numpy.py
dslinter/checkers/deprecated/mode_toggling_pytorch.py
dslinter/checkers/deterministic_pytorch.py
dslinter/checkers/forward_pytorch.py
dslinter/checkers/gradient_clear_pytorch.py
dslinter/checkers/hyperparameters.py
dslinter/checkers/hyperparameters_pytorch.py
dslinter/checkers/hyperparameters_scikitlearn.py
dslinter/checkers/hyperparameters_tensorflow.py
dslinter/checkers/imports.py
dslinter/checkers/inplace_pandas.py
dslinter/checkers/mask_missing_pytorch.py
dslinter/checkers/mask_missing_tensorflow.py
dslinter/checkers/memory_release_tensorflow.py
dslinter/checkers/merge_parameter_pandas.py
dslinter/checkers/nan_numpy.py
dslinter/checkers/pipeline_scikitlearn.py
dslinter/checkers/randomness_control_dataloader_pytorch.py
dslinter/checkers/randomness_control_numpy.py
dslinter/checkers/randomness_control_pytorch.py
dslinter/checkers/randomness_control_scikitlearn.py
dslinter/checkers/randomness_control_tensorflow.py
dslinter/checkers/scaler_missing_scikitlearn.py
dslinter/checkers/tensor_array_tensorflow.py
dslinter/checkers/unnecessary_iteration_pandas.py
dslinter/checkers/unnecessary_iteration_tensorflow.py
dslinter/plugin.py
dslinter/resources/__init__.py
dslinter/resources/hyperparameters_pytorch_dict.pickle
dslinter/resources/hyperparameters_scikitlearn_dict.pickle
dslinter/resources/hyperparameters_tensorflow_dict.pickle
dslinter/scripts/__init__.py
dslinter/scripts/hyperparameters.py
dslinter/scripts/hyperparameters_pytorch.py
dslinter/scripts/hyperparameters_scikitlearn.py
dslinter-2.0.9.dist-info/LICENSE
dslinter-2.0.9.dist-info/WHEEL
dslinter-2.0.9.dist-info/METADATA
dslinter-2.0.9.dist-info/RECORD
