Metadata-Version: 2.1
Name: dslinter
Version: 2.0.9
Summary: `dslinter` is a pylint plugin for linting data science and machine learning code. We plan to support the following Python libraries: TensorFlow, PyTorch, Scikit-Learn, Pandas, NumPy and SciPy.
Home-page: https://pypi.org/project/dslinter/
License: GPL-3.0 License
Keywords: machine learning,software engineering
Author: Mark Haakman
Requires-Python: >=3.7,<4.0
Classifier: License :: Other/Proprietary License
Classifier: Programming Language :: Python :: 3
Classifier: Programming Language :: Python :: 3.10
Classifier: Programming Language :: Python :: 3.7
Classifier: Programming Language :: Python :: 3.8
Classifier: Programming Language :: Python :: 3.9
Requires-Dist: astroid (>=2.9.3,<2.10.0)
Requires-Dist: data-science-types (>=0.2.23,<0.3.0)
Requires-Dist: mypy (>=0.931,<0.932)
Requires-Dist: pylint (>=2.12.2,<2.13.0)
Requires-Dist: pyspark-stubs (>=3.0.0.post3,<3.1.0)
Requires-Dist: toml (>=0.10,<0.11)
Project-URL: Repository, https://github.com/SERG-Delft/dslinter
